adptools/VariableSelector.py
adptools/__init__.py
adptools/graphics.py
adptools/pca.py
adptools/preprocessing.py
adptools-0.0.1.7.dist-info/LICENSE.txt
adptools-0.0.1.7.dist-info/METADATA
adptools-0.0.1.7.dist-info/WHEEL
adptools-0.0.1.7.dist-info/top_level.txt
adptools-0.0.1.7.dist-info/RECORD
