Metadata-Version: 2.1
Name: adptools
Version: 0.0.1.7
Summary: A package for ADP license. It contains PCA(Scree plot etc.) and Variable Selection tools.
Home-page: https://github.com/hrdkdh/adptools
Author: duhwan kim
Author-email: hrdkdh@naver.com
License: UNKNOWN
Platform: UNKNOWN
Classifier: Programming Language :: Python :: 3
Classifier: License :: OSI Approved :: MIT License
Classifier: Operating System :: OS Independent
Requires-Python: >=3.6
